LICENSE
MANIFEST.in
README.rst
VERSION
setup.py
django_rocket_engine.egg-info/PKG-INFO
django_rocket_engine.egg-info/SOURCES.txt
django_rocket_engine.egg-info/dependency_links.txt
django_rocket_engine.egg-info/requires.txt
django_rocket_engine.egg-info/top_level.txt
rocket_engine/__init__.py
rocket_engine/mail.py
rocket_engine/models.py
rocket_engine/storage.py
rocket_engine/tasks.py
rocket_engine/utils.py
rocket_engine/views.py
rocket_engine/db/__init__.py
rocket_engine/db/backends/__init__.py
rocket_engine/db/backends/cloudsql/__init__.py
rocket_engine/db/backends/cloudsql/base.py
rocket_engine/management/__init__.py
rocket_engine/management/commands/__init__.py
rocket_engine/management/commands/appengine.py
rocket_engine/management/commands/on_appengine.py
rocket_engine/management/commands/runserver.py
tests/__init__.py
tests/models.py
tests/runtests.py
tests/tests.py