Metadata-Version: 1.1
Name: django-rocket-engine
Version: 0.0.11
Summary: Django on Google AppEngine
Home-page: http://readthedocs.org/projects/django-rocket-engine/
Author: Sebastian Pawluś
Author-email: sebastian.pawlus@gmail.com
License: Copyright (c) 2012, Sebastian Pawluś.
